[
	{
		"constant": false,
		"inputs": [],
		"name": "emitMortgage",
		"outputs": [],
		"payable": false,
		"stateMutability": "nonpayable",
		"type": "function"
	},
	{
		"constant": false,
		"inputs": [
			{
				"name": "_currentBalance",
				"type": "uint256"
			}
		],
		"name": "setCurrentBalance",
		"outputs": [],
		"payable": false,
		"stateMutability": "nonpayable",
		"type": "function"
	},
	{
		"constant": false,
		"inputs": [
			{
				"name": "_mortgageAmount",
				"type": "uint256"
			}
		],
		"name": "setMortgageAmount",
		"outputs": [],
		"payable": false,
		"stateMutability": "nonpayable",
		"type": "function"
	},
	{
		"constant": false,
		"inputs": [
			{
				"name": "_owner",
				"type": "string"
			}
		],
		"name": "setOwner",
		"outputs": [],
		"payable": false,
		"stateMutability": "nonpayable",
		"type": "function"
	},
	{
		"constant": false,
		"inputs": [
			{
				"name": "_status",
				"type": "string"
			}
		],
		"name": "setStatus",
		"outputs": [],
		"payable": false,
		"stateMutability": "nonpayable",
		"type": "function"
	},
	{
		"anonymous": false,
		"inputs": [
			{
				"indexed": false,
				"name": "_from",
				"type": "address"
			},
			{
				"indexed": false,
				"name": "_houseAddress",
				"type": "string"
			},
			{
				"indexed": false,
				"name": "_owner",
				"type": "string"
			},
			{
				"indexed": false,
				"name": "_mortgageAmount",
				"type": "uint256"
			},
			{
				"indexed": false,
				"name": "_currentBalance",
				"type": "uint256"
			},
			{
				"indexed": false,
				"name": "_status",
				"type": "string"
			}
		],
		"name": "Mortgage",
		"type": "event"
	},
	{
		"constant": true,
		"inputs": [],
		"name": "currentBalance",
		"outputs": [
			{
				"name": "",
				"type": "uint256"
			}
		],
		"payable": false,
		"stateMutability": "view",
		"type": "function"
	},
	{
		"constant": true,
		"inputs": [],
		"name": "houseAddress",
		"outputs": [
			{
				"name": "",
				"type": "string"
			}
		],
		"payable": false,
		"stateMutability": "view",
		"type": "function"
	},
	{
		"constant": true,
		"inputs": [],
		"name": "mortgageAmount",
		"outputs": [
			{
				"name": "",
				"type": "uint256"
			}
		],
		"payable": false,
		"stateMutability": "view",
		"type": "function"
	},
	{
		"constant": true,
		"inputs": [],
		"name": "owner",
		"outputs": [
			{
				"name": "",
				"type": "string"
			}
		],
		"payable": false,
		"stateMutability": "view",
		"type": "function"
	},
	{
		"constant": true,
		"inputs": [],
		"name": "status",
		"outputs": [
			{
				"name": "",
				"type": "string"
			}
		],
		"payable": false,
		"stateMutability": "view",
		"type": "function"
	}
]